xml_default_dict/__init__.py
xml_default_dict/save_xml_dict.py
xml_default_dict/xml_default_dict.py
xml_default_dict-0.2.data/data/LICENSE
xml_default_dict-0.2.dist-info/DESCRIPTION.rst
xml_default_dict-0.2.dist-info/METADATA
xml_default_dict-0.2.dist-info/RECORD
xml_default_dict-0.2.dist-info/WHEEL
xml_default_dict-0.2.dist-info/metadata.json
xml_default_dict-0.2.dist-info/top_level.txt
