Metadata-Version: 2.0
Name: xml-default-dict
Version: 0.2
Summary: A simple way to convert xml elemnts into a default dict from lib collections.
Home-page: https://github.com/kanazux/xml-default-dict
Author: Silvio AS a.k.a kanazuchi
Author-email: contato@kanazuchi.com
License: BSD2CLAUSE
Keywords: xml dict defaultdict
Platform: UNKNOWN
